odoo9_addon_donation_recurring-9.0.1.0.0.99.dev4-py2.7-nspkg.pth
odoo9_addon_donation_recurring-9.0.1.0.0.99.dev4.dist-info/DESCRIPTION.rst
odoo9_addon_donation_recurring-9.0.1.0.0.99.dev4.dist-info/METADATA
odoo9_addon_donation_recurring-9.0.1.0.0.99.dev4.dist-info/RECORD
odoo9_addon_donation_recurring-9.0.1.0.0.99.dev4.dist-info/WHEEL
odoo9_addon_donation_recurring-9.0.1.0.0.99.dev4.dist-info/metadata.json
odoo9_addon_donation_recurring-9.0.1.0.0.99.dev4.dist-info/namespace_packages.txt
odoo9_addon_donation_recurring-9.0.1.0.0.99.dev4.dist-info/top_level.txt
odoo_addons/donation_recurring/README.rst
odoo_addons/donation_recurring/__init__.py
odoo_addons/donation_recurring/__openerp__.py
odoo_addons/donation_recurring/demo/donation_recurring_demo.xml
odoo_addons/donation_recurring/i18n/fr.po
odoo_addons/donation_recurring/models/__init__.py
odoo_addons/donation_recurring/models/donation.py
odoo_addons/donation_recurring/static/description/icon.png
odoo_addons/donation_recurring/tests/__init__.py
odoo_addons/donation_recurring/tests/test_recurring_donations.py
odoo_addons/donation_recurring/views/donation.xml
odoo_addons/donation_recurring/wizard/__init__.py
odoo_addons/donation_recurring/wizard/donation_recurring_generate.py
odoo_addons/donation_recurring/wizard/donation_recurring_generate_view.xml
